<Properties StartupConfiguration="{0C549892-51FC-44E2-998D-B78069C11D16}|Default">
  <MonoDevelop.Ide.ItemProperties.Constructors PreferredExecutionTarget="MonoDevelop.Default" FirstBuild="True" />
  <MonoDevelop.Ide.Workspace ActiveConfiguration="Debug" />
  <MonoDevelop.Ide.DebuggingService.PinnedWatches />
  <MonoDevelop.Ide.Workbench ActiveDocument="Constructors/Program.cs">
    <Files>
      <File FileName="Constructors/Program.cs" Line="5" Column="13" />
      <File FileName="Constructors/NetworkHelper.cs" Line="10" Column="16" />
    </Files>
    <Pads>
      <Pad Id="ProjectPad">
        <State name="__root__">
          <Node name="Constructors" expanded="True" selected="True">
            <Node name="Constructors" expanded="True" />
          </Node>
        </State>
      </Pad>
    </Pads>
  </MonoDevelop.Ide.Workbench>
  <MonoDevelop.Ide.DebuggingService.Breakpoints>
    <BreakpointStore />
  </MonoDevelop.Ide.DebuggingService.Breakpoints>
  <MultiItemStartupConfigurations />
</Properties>